ommx_qctrl_qaoa_adapter/__init__.py
ommx_qctrl_qaoa_adapter/_version.py
ommx_qctrl_qaoa_adapter/adapter.py
ommx_qctrl_qaoa_adapter/exception.py
ommx_qctrl_qaoa_adapter-0.1.0.dist-info/licenses/LICENSE
ommx_qctrl_qaoa_adapter-0.1.0.dist-info/METADATA
ommx_qctrl_qaoa_adapter-0.1.0.dist-info/WHEEL
ommx_qctrl_qaoa_adapter-0.1.0.dist-info/top_level.txt
ommx_qctrl_qaoa_adapter-0.1.0.dist-info/RECORD
