Metadata-Version: 2.4
Name: ommx-qctrl-qaoa-adapter
Version: 0.1.0
Summary: OMMX adapter for fireopal.solve_qaoa
Requires-Python: >=3.12
License-File: LICENSE
Requires-Dist: ommx>=2.0.0
Requires-Dist: fire-opal>=8.1.0
Requires-Dist: sympy>=1.12
Dynamic: license-file
